pyDownload/__init__.py
pyDownload/__main__.py
pyDownload/downloader.py
pyDownload/file_manager.py
pyDownload/utils.py
pyDownload-0.0.1.dev4.dist-info/METADATA
pyDownload-0.0.1.dev4.dist-info/RECORD
pyDownload-0.0.1.dev4.dist-info/WHEEL
pyDownload-0.0.1.dev4.dist-info/entry_points.txt
pyDownload-0.0.1.dev4.dist-info/top_level.txt
