Metadata-Version: 2.1
Name: pyDownload
Version: 0.0.1.dev4
Summary: A simple package for multithreaded downloading
Home-page: https://github.com/party98/Python-Parallel-Downloader
Author: Parth Verma
Author-email: v.parth98@gmail.com
License: UNKNOWN
Project-URL: Source, https://github.com/party98/Python-Parallel-Downloader
Project-URL: Bug Reports, https://github.com/party98/Python-Parallel-Downloader/issues
Project-URL: Say Thanks!, https://saythanks.io/to/party98
Keywords: downloading multithreaded parallel multithreading multithreaded-downloading download
Platform: UNKNOWN
Classifier: Development Status :: 4 - Beta
Classifier: Intended Audience :: Developers
Classifier: License :: OSI Approved :: GNU Affero General Public License v3 or later (AGPLv3+)
Classifier: Programming Language :: Python :: 2
Classifier: Programming Language :: Python :: 2.7
Classifier: Programming Language :: Python :: 3
Classifier: Programming Language :: Python :: 3.4
Classifier: Programming Language :: Python :: 3.5
Classifier: Programming Language :: Python :: 3.6
Provides-Extra: dev
Provides-Extra: test
Requires-Dist: requests (>=2.18.0)
Requires-Dist: progressbar2 (>=3.37.1)
Provides-Extra: dev
Requires-Dist: pre-commit (==1.8.2); extra == 'dev'
Provides-Extra: test
Requires-Dist: nose; extra == 'test'
Requires-Dist: coverage; extra == 'test'
